markarth/__init__.py
markarth/ast_utils/__init__.py
markarth/ast_utils/ast_utils.py
markarth/convert/__init__.py
markarth/convert/convert_pure.py
markarth/convert/collect/__init__.py
markarth/convert/collect/func_collect.py
markarth/convert/collect/mod_collect.py
markarth/convert/collect/vartyp_tracker.py
markarth/convert/collect/ast_to_typ/__init__.py
markarth/convert/collect/ast_to_typ/ast_assign.py
markarth/convert/collect/ast_to_typ/ast_to_typ.py
markarth/convert/cythonize/__init__.py
markarth/convert/cythonize/cy_options.py
markarth/convert/cythonize/cy_typs.py
markarth/convert/cythonize/pure.py
markarth/convert/preprocess/__init__.py
markarth/convert/preprocess/code_process.py
markarth/convert/typs/__init__.py
markarth/convert/typs/merge_typs.py
markarth/convert/typs/typ_store.py
markarth/convert/typs/typs.py
markarth/convert/typs/typs_parse.py
markarth-0.0.5.dist-info/LICENSE
markarth-0.0.5.dist-info/METADATA
markarth-0.0.5.dist-info/WHEEL
markarth-0.0.5.dist-info/top_level.txt
markarth-0.0.5.dist-info/RECORD
