Metadata-Version: 2.1
Name: markarth
Version: 0.0.5
Summary: Automatic code conversion from python to cython
Home-page: https://github.com/nucccc/markarth
Author: Domenico Nucera
License: MIT License
Classifier: Development Status :: 3 - Alpha
Classifier: Intended Audience :: Developers
Classifier: License :: OSI Approved :: MIT License
Classifier: Operating System :: OS Independent
Classifier: Programming Language :: Python
Classifier: Programming Language :: Python :: 3
Classifier: Programming Language :: Python :: 3 :: Only
Classifier: Programming Language :: Python :: 3.9
Classifier: Programming Language :: Python :: 3.10
Classifier: Programming Language :: Python :: 3.11
Classifier: Programming Language :: Python :: 3.12
Classifier: Topic :: Software Development :: Code Generators
License-File: LICENSE
Requires-Dist: pydantic >=2.4.2
Requires-Dist: coverage >=7.3.2
